MANIFEST.in
README.md
requerimientos.txt
setup.cfg
setup.py
precisionpredictiva/__init__.py
precisionpredictiva/conjunto_entrenamiento.py
precisionpredictiva/dataset.py
precisionpredictiva/datasets_incorporados.py
precisionpredictiva/dump.py
precisionpredictiva/metricas_similitud.c
precisionpredictiva/metricas_similitud.pyx
precisionpredictiva/precision.py
precisionpredictiva/reader.py
precisionpredictiva/utilidades.py
precisionpredictiva/algoritmos_predictivos/__init__.py
precisionpredictiva/algoritmos_predictivos/algo_base.py
precisionpredictiva/algoritmos_predictivos/factorizacion_matricial.c
precisionpredictiva/algoritmos_predictivos/factorizacion_matricial.pyx
precisionpredictiva/algoritmos_predictivos/knn.py
precisionpredictiva/algoritmos_predictivos/optimizador_sesgos.c
precisionpredictiva/algoritmos_predictivos/optimizador_sesgos.pyx
precisionpredictiva/algoritmos_predictivos/predicciones.py
precisionpredictiva/algoritmos_predictivos/predictor_base.py
precisionpredictiva/iteradores/__init__.py
precisionpredictiva/iteradores/split.py
precisionpredictiva/iteradores/validacion.py
scikit_predictiveaccuracy.egg-info/PKG-INFO
scikit_predictiveaccuracy.egg-info/SOURCES.txt
scikit_predictiveaccuracy.egg-info/dependency_links.txt
scikit_predictiveaccuracy.egg-info/requires.txt
scikit_predictiveaccuracy.egg-info/top_level.txt