Metadata-Version: 1.1
Name: scikit-predictiveaccuracy
Version: 1.0.0
Summary: Predictive accuracy of recommendation system algorithms.
Home-page: UNKNOWN
Author: Marcos Dumón
Author-email: mdumon11@gmail.com
License: GPLv3+
Platform: UNKNOWN
Classifier: Development Status :: 4 - Beta
Classifier: Intended Audience :: Developers
Classifier: Intended Audience :: Science/Research
Classifier: Intended Audience :: Education
Classifier: Topic :: Scientific/Engineering
Classifier: Programming Language :: Python :: 3
Classifier: Programming Language :: Python :: 2.7
